odoo/addons/fieldservice_account_payment/README.rst
odoo/addons/fieldservice_account_payment/__init__.py
odoo/addons/fieldservice_account_payment/__manifest__.py
odoo/addons/fieldservice_account_payment/i18n/es.po
odoo/addons/fieldservice_account_payment/i18n/es_AR.po
odoo/addons/fieldservice_account_payment/i18n/es_CL.po
odoo/addons/fieldservice_account_payment/i18n/fieldservice_account_payment.pot
odoo/addons/fieldservice_account_payment/i18n/it.po
odoo/addons/fieldservice_account_payment/i18n/pt_BR.po
odoo/addons/fieldservice_account_payment/models/__init__.py
odoo/addons/fieldservice_account_payment/models/account_payment.py
odoo/addons/fieldservice_account_payment/models/fsm_order.py
odoo/addons/fieldservice_account_payment/readme/CONFIGURE.rst
odoo/addons/fieldservice_account_payment/readme/CONTRIBUTORS.rst
odoo/addons/fieldservice_account_payment/readme/CREDITS.rst
odoo/addons/fieldservice_account_payment/readme/DESCRIPTION.rst
odoo/addons/fieldservice_account_payment/readme/INSTALL.rst
odoo/addons/fieldservice_account_payment/readme/USAGE.rst
odoo/addons/fieldservice_account_payment/security/ir.model.access.csv
odoo/addons/fieldservice_account_payment/static/description/icon.png
odoo/addons/fieldservice_account_payment/static/description/index.html
odoo/addons/fieldservice_account_payment/tests/__init__.py
odoo/addons/fieldservice_account_payment/tests/test_fsm_account_payment.py
odoo/addons/fieldservice_account_payment/views/account_payment.xml
odoo/addons/fieldservice_account_payment/views/fsm_order.xml
odoo14_addon_fieldservice_account_payment-14.0.1.0.1.dist-info/METADATA
odoo14_addon_fieldservice_account_payment-14.0.1.0.1.dist-info/WHEEL
odoo14_addon_fieldservice_account_payment-14.0.1.0.1.dist-info/top_level.txt
odoo14_addon_fieldservice_account_payment-14.0.1.0.1.dist-info/RECORD
